promptscreen/__init__.py
promptscreen/cli.py
promptscreen/api/__init__.py
promptscreen/api/server.py
promptscreen/data/__init__.py
promptscreen/data/rules/apitokens.yar
promptscreen/data/rules/generic_secret.yar
promptscreen/data/rules/guidance.yar
promptscreen/data/rules/instruction_bypass.yar
promptscreen/data/rules/ip.yar
promptscreen/data/rules/mdexfil.yar
promptscreen/data/rules/react.yar
promptscreen/data/rules/react_txt.yar
promptscreen/data/rules/ssh.yar
promptscreen/data/rules/system_instructions.yar
promptscreen/defence/__init__.py
promptscreen/defence/abstract_defence.py
promptscreen/defence/classifier_cluster.py
promptscreen/defence/heuristic_channel.py
promptscreen/defence/injection_regex.py
promptscreen/defence/linear_svm.py
promptscreen/defence/ppa_defence.py
promptscreen/defence/ppa_defense_demo.py
promptscreen/defence/scanner.py
promptscreen/defence/shieldgemma.py
promptscreen/defence/vectordb.py
promptscreen/defence/ds/__init__.py
promptscreen/defence/ds/analysis_result.py
promptscreen/defence/train/__init__.py
promptscreen/defence/train/train_classifier.py
promptscreen/evaluation/__init__.py
promptscreen/evaluation/ds_metrics.py
promptscreen/evaluation/metrics_classes.py
promptscreen/evaluation/pipeline.py
promptscreen/output_scanners/__init__.py
promptscreen/output_scanners/scan.py
promptscreen/utils/__init__.py
promptscreen/utils/query_agent.py
promptscreen-0.3.0.dist-info/licenses/LICENSE
promptscreen-0.3.0.dist-info/METADATA
promptscreen-0.3.0.dist-info/WHEEL
promptscreen-0.3.0.dist-info/entry_points.txt
promptscreen-0.3.0.dist-info/top_level.txt
promptscreen-0.3.0.dist-info/RECORD
