Metadata-Version: 2.4
Name: promptscreen
Version: 0.3.0
Summary: Prompt injection defense for LLMs
Author-email: Akshaj Rao <kumaar324@gmail.com>, Advait Singh <kumaar324@gmail.com>, Saumya Saksena <kumaar324@gmail.com>
License: Apache-2.0
Project-URL: Homepage, https://github.com/dronefreak/PromptScreen
Project-URL: Repository, https://github.com/dronefreak/PromptScreen
Project-URL: Documentation, https://github.com/dronefreak/PromptScreen#readme
Project-URL: Issues, https://github.com/dronefreak/PromptScreen/issues
Keywords: llm,prompt-injection,jailbreak,security,ai-safety
Classifier: Development Status :: 3 - Alpha
Classifier: Intended Audience :: Developers
Classifier: License :: OSI Approved :: Apache Software License
Classifier: Programming Language :: Python :: 3
Classifier: Programming Language :: Python :: 3.9
Classifier: Programming Language :: Python :: 3.10
Classifier: Programming Language :: Python :: 3.11
Classifier: Programming Language :: Python :: 3.12
Classifier: Topic :: Security
Classifier: Topic :: Scientific/Engineering :: Artificial Intelligence
Requires-Python: >=3.9
License-File: LICENSE
Requires-Dist: scikit-learn>=1.2.0
Requires-Dist: joblib>=1.5.0
Requires-Dist: yara-python>=4.3.0
Requires-Dist: emoji>=2.0.0
Requires-Dist: nltk>=3.9.0
Requires-Dist: numpy>=1.24.0
Requires-Dist: pandas>=2.0.0
Requires-Dist: typing-extensions>=4.5.0
Provides-Extra: ml
Requires-Dist: torch>=2.0.0; extra == "ml"
Requires-Dist: transformers>=4.30.0; extra == "ml"
Requires-Dist: sentence-transformers>=2.0.0; extra == "ml"
Provides-Extra: vectordb
Requires-Dist: chromadb>=0.4.0; extra == "vectordb"
Requires-Dist: pydantic>=2.0.0; extra == "vectordb"
Provides-Extra: api
Requires-Dist: fastapi>=0.100.0; extra == "api"
Requires-Dist: uvicorn>=0.20.0; extra == "api"
Requires-Dist: pydantic>=2.0.0; extra == "api"
Provides-Extra: eval
Requires-Dist: langchain-ollama>=1.0.0; extra == "eval"
Requires-Dist: omegaconf>=2.3.0; extra == "eval"
Requires-Dist: hydra-core>=1.3.0; extra == "eval"
Provides-Extra: all
Requires-Dist: torch>=2.0.0; extra == "all"
Requires-Dist: transformers>=4.30.0; extra == "all"
Requires-Dist: sentence-transformers>=2.0.0; extra == "all"
Requires-Dist: chromadb>=0.4.0; extra == "all"
Requires-Dist: fastapi>=0.100.0; extra == "all"
Requires-Dist: uvicorn>=0.20.0; extra == "all"
Requires-Dist: langchain-ollama>=1.0.0; extra == "all"
Requires-Dist: omegaconf>=2.3.0; extra == "all"
Requires-Dist: hydra-core>=1.3.0; extra == "all"
Provides-Extra: dev
Requires-Dist: pytest>=7.4.0; extra == "dev"
Requires-Dist: pytest-cov>=4.1.0; extra == "dev"
Requires-Dist: pytest-asyncio>=0.21.0; extra == "dev"
Requires-Dist: pytest-mock>=3.11.0; extra == "dev"
Requires-Dist: black>=23.12.0; extra == "dev"
Requires-Dist: ruff>=0.14.5; extra == "dev"
Requires-Dist: mypy>=1.8.0; extra == "dev"
Requires-Dist: bandit[toml]>=1.7.6; extra == "dev"
Requires-Dist: pre-commit>=3.5.0; extra == "dev"
Requires-Dist: types-requests>=2.31.0; extra == "dev"
Requires-Dist: types-PyYAML>=6.0.0; extra == "dev"
Requires-Dist: pydocstyle>=6.3.0; extra == "dev"
Requires-Dist: yamllint>=1.33.0; extra == "dev"
Requires-Dist: fastapi>=0.100.0; extra == "dev"
Requires-Dist: chromadb>=1.2.0; extra == "dev"
Requires-Dist: lark>=1.2.0; extra == "dev"
Requires-Dist: httpx>=0.25.0; extra == "dev"
Requires-Dist: hydra-core>=1.3.0; extra == "dev"
Requires-Dist: langchain_google_genai>=2.0.0; extra == "dev"
Requires-Dist: langchain_ollama>=0.3.0; extra == "dev"
Dynamic: license-file
